Metadata-Version: 2.1
Name: digipathos
Version: 0.2.4
Summary: UNKNOWN
Home-page: https://github.com/bresan/digipathos_plant_pathology
Author: Rodrigo Bresan
Author-email: 
License: BSD-3-Clause
Platform: UNKNOWN
Classifier: Programming Language :: Python :: 3.6
Requires-Dist: atomicwrites (==1.3.0)
Requires-Dist: attrs (==19.1.0)
Requires-Dist: certifi (==2019.3.9)
Requires-Dist: chardet (==3.0.4)
Requires-Dist: codecov (==2.0.15)
Requires-Dist: coverage (==4.5.3)
Requires-Dist: idna (==2.8)
Requires-Dist: more-itertools (==6.0.0)
Requires-Dist: mypy (==0.670)
Requires-Dist: mypy-extensions (==0.4.1)
Requires-Dist: pluggy (==0.9.0)
Requires-Dist: py (==1.8.0)
Requires-Dist: pytest (==4.3.1)
Requires-Dist: pytest-cov (==2.6.1)
Requires-Dist: requests (==2.21.0)
Requires-Dist: six (==1.12.0)
Requires-Dist: terminaltables (==3.1.0)
Requires-Dist: typed-ast (==1.3.1)
Requires-Dist: urllib3 (==1.24.1)
